structly_whois/__about__.py
structly_whois/__init__.py
structly_whois/cli.py
structly_whois/config.py
structly_whois/domain_inference.py
structly_whois/normalization.py
structly_whois/parser.py
structly_whois/py.typed
structly_whois/config/__init__.py
structly_whois/config/factory.py
structly_whois/config/fields.py
structly_whois/config/tlds.py
structly_whois/records/__init__.py
structly_whois/records/builder.py
structly_whois/records/models.py
structly_whois/records/utils.py
structly_whois-1.1.0.dist-info/METADATA
structly_whois-1.1.0.dist-info/WHEEL
structly_whois-1.1.0.dist-info/entry_points.txt
structly_whois-1.1.0.dist-info/licenses/LICENSE
structly_whois-1.1.0.dist-info/RECORD
