Metadata-Version: 2.4
Name: structly-whois
Version: 1.1.0
Summary: Fast WHOIS parsing core with a Pythonic surface area.
Project-URL: Homepage, https://github.com/bytevader/structly-whois-parser
Project-URL: Repository, https://github.com/bytevader/structly-whois-parser
Project-URL: Issues, https://github.com/bytevader/structly-whois-parser/issues
Project-URL: Changelog, https://github.com/bytevader/structly-whois-parser/blob/main/CHANGELOG.md
Project-URL: Documentation, https://github.com/bytevader/structly-whois-parser/blob/main/README.md
Author-email: Nikola Stankovic <nstankovic.bg@proton.me>
License: MIT License
License-File: LICENSE
Keywords: domain,parser,structly,whois
Classifier: Development Status :: 4 - Beta
Classifier: Intended Audience :: Developers
Classifier: License :: OSI Approved :: MIT License
Classifier: Operating System :: OS Independent
Classifier: Programming Language :: Python :: 3
Classifier: Topic :: Internet :: Name Service (DNS)
Classifier: Topic :: Software Development :: Libraries :: Python Modules
Requires-Python: >=3.9
Requires-Dist: msgspec>=0.18
Requires-Dist: structly>=1.0.1
Provides-Extra: benchmarks
Requires-Dist: confluent-kafka>=2.3; extra == 'benchmarks'
Requires-Dist: dateparser>=1.2; extra == 'benchmarks'
Requires-Dist: orjson>=3.9; extra == 'benchmarks'
Requires-Dist: python-snappy>=0.6; extra == 'benchmarks'
Provides-Extra: dev
Requires-Dist: build>=1.2; extra == 'dev'
Requires-Dist: confluent-kafka>=2.3; extra == 'dev'
Requires-Dist: hypothesis>=6.100; extra == 'dev'
Requires-Dist: maturin>=1.5.1; extra == 'dev'
Requires-Dist: orjson>=3.9; extra == 'dev'
Requires-Dist: psutil>=5.9; extra == 'dev'
Requires-Dist: pytest-cov>=5.0; extra == 'dev'
Requires-Dist: pytest>=8.2; extra == 'dev'
Requires-Dist: python-snappy>=0.6; extra == 'dev'
Requires-Dist: python-whois>=0.9; extra == 'dev'
Requires-Dist: ruff>=0.5; extra == 'dev'
Requires-Dist: tabulate>=0.9; extra == 'dev'
Requires-Dist: whois-parser; extra == 'dev'
